LICENSE
MANIFEST.in
getting started.ipynb
setup.cfg
setup.py
magical/__init__.py
magical/magic.py
magical/recipes.py
magical_magic.egg-info/PKG-INFO
magical_magic.egg-info/SOURCES.txt
magical_magic.egg-info/dependency_links.txt
magical_magic.egg-info/requires.txt
magical_magic.egg-info/top_level.txt